kisa.py
whois.py
pkgs_bob8gook-1.0.0.7.dist-info/METADATA
pkgs_bob8gook-1.0.0.7.dist-info/WHEEL
pkgs_bob8gook-1.0.0.7.dist-info/top_level.txt
pkgs_bob8gook-1.0.0.7.dist-info/RECORD
